README.rst
setup.py
gitdh/__init__.py
gitdh/cli.py
gitdh/config.py
gitdh/database.py
gitdh/git.py
gitdh/gitdh.py
gitdh/gitdhutils.py
gitdh/module.py
gitdh.egg-info/PKG-INFO
gitdh.egg-info/SOURCES.txt
gitdh.egg-info/dependency_links.txt
gitdh.egg-info/entry_points.txt
gitdh.egg-info/requires.txt
gitdh.egg-info/top_level.txt
gitdh/modules/__init__.py
gitdh/modules/approval.py
gitdh/modules/commandprocessing.py
gitdh/modules/crondeployment.py
gitdh/modules/databaselog.py
gitdh/modules/databasesource.py
gitdh/modules/deployment.py
gitdh/modules/external.py
gitdh/modules/postreceivesource.py