Metadata-Version: 1.1
Name: gitdh
Version: 0.7.4
Summary: Tool to automatically deploy git commits using post-receive hooks and cron jobs
Home-page: https://github.com/seoester/Git-Deployment-Handler
Author: Seoester
Author-email: seoester@googlemail.com
License: MIT
Keywords: git deploy deployment commit database remote approval cron post-receive hook
Platform: UNKNOWN
Classifier: Development Status :: 4 - Beta
Classifier: License :: OSI Approved :: MIT License
Classifier: Operating System :: POSIX :: Linux
Classifier: Programming Language :: Python :: 3
Classifier: Programming Language :: Python :: 3.2
Classifier: Programming Language :: Python :: 3.3
Classifier: Programming Language :: Python :: 3.4
Classifier: Topic :: Software Development :: Version Control
Provides: gitdh
